htv_patch_m3u8.py
htv_search.py
yt_dlp_plugins/extractor/htv.py
hanime_tv_plugin-2025.6.6.dist-info/LICENSE
hanime_tv_plugin-2025.6.6.dist-info/METADATA
hanime_tv_plugin-2025.6.6.dist-info/WHEEL
hanime_tv_plugin-2025.6.6.dist-info/entry_points.txt
hanime_tv_plugin-2025.6.6.dist-info/RECORD
