Metadata-Version: 2.3
Name: hanime-tv-plugin
Version: 2025.6.6
Summary: hanime.tv extractor plugin for yt-dlp
Author: Cynthia
Author-email: cynthia2048@proton.me
Requires-Python: >=3.9
Classifier: Programming Language :: Python :: 3
Classifier: Programming Language :: Python :: 3.9
Classifier: Programming Language :: Python :: 3.10
Classifier: Programming Language :: Python :: 3.11
Classifier: Programming Language :: Python :: 3.12
Classifier: Programming Language :: Python :: 3.13
Requires-Dist: m3u8 (>=6.0.0,<7.0.0)
